shortcut_alias/__init__.py
shortcut_alias/__main__.py
shortcut_alias/commands.py
shortcut_alias/exceptions.py
shortcut_alias/options.py
shortcut_alias/shortcut.py
shortcut_alias/variables.py
shortcut_alias-0.2.6.dist-info/entry_points.txt
shortcut_alias-0.2.6.dist-info/LICENSE
shortcut_alias-0.2.6.dist-info/WHEEL
shortcut_alias-0.2.6.dist-info/METADATA
shortcut_alias-0.2.6.dist-info/RECORD
