Metadata-Version: 2.1
Name: shortcut-alias
Version: 0.2.6
Summary: Powerful Configurable Aliases
Keywords: alias,shortcut,shortcut_alias
Author-email: Matt Limb <matt.limb17@gmail.com>
Requires-Python: >=3.6
Classifier: Programming Language :: Python :: 3
Classifier: License :: OSI Approved :: GNU General Public License v2 (GPLv2)
Classifier: Operating System :: OS Independent
Requires-Dist: colorama==0.4.4
Requires-Dist: Jinja2==2.11.3
Requires-Dist: MarkupSafe==1.1.1
Requires-Dist: PyYAML==5.4.1
Requires-Dist: termcolor==1.1.0
Project-URL: homepage, https://github.com/MattLimb/shortcut-alias/
